CHANGES.rst
CONTRIBUTORS.rst
DEVELOP.rst
LICENSE.GPL
LICENSE.rst
MANIFEST.in
README.rst
constraints.txt
constraints_plone52.txt
requirements.txt
setup.cfg
setup.py
docs/conf.py
docs/index.rst
src/collective/__init__.py
src/collective.volto.cookieconsent.egg-info/PKG-INFO
src/collective.volto.cookieconsent.egg-info/SOURCES.txt
src/collective.volto.cookieconsent.egg-info/dependency_links.txt
src/collective.volto.cookieconsent.egg-info/entry_points.txt
src/collective.volto.cookieconsent.egg-info/namespace_packages.txt
src/collective.volto.cookieconsent.egg-info/not-zip-safe
src/collective.volto.cookieconsent.egg-info/requires.txt
src/collective.volto.cookieconsent.egg-info/top_level.txt
src/collective/volto/__init__.py
src/collective/volto/cookieconsent/__init__.py
src/collective/volto/cookieconsent/configure.zcml
src/collective/volto/cookieconsent/interfaces.py
src/collective/volto/cookieconsent/setuphandlers.py
src/collective/volto/cookieconsent/testing.py
src/collective/volto/cookieconsent/browser/__init__.py
src/collective/volto/cookieconsent/browser/configure.zcml
src/collective/volto/cookieconsent/browser/controlpanel.py
src/collective/volto/cookieconsent/locales/README.rst
src/collective/volto/cookieconsent/locales/__init__.py
src/collective/volto/cookieconsent/locales/collective.volto.cookieconsent.pot
src/collective/volto/cookieconsent/locales/update.py
src/collective/volto/cookieconsent/locales/update.sh
src/collective/volto/cookieconsent/locales/en/LC_MESSAGES/collective.volto.cookieconsent.mo
src/collective/volto/cookieconsent/locales/en/LC_MESSAGES/collective.volto.cookieconsent.po
src/collective/volto/cookieconsent/locales/it/LC_MESSAGES/collective.volto.cookieconsent.mo
src/collective/volto/cookieconsent/locales/it/LC_MESSAGES/collective.volto.cookieconsent.po
src/collective/volto/cookieconsent/profiles/default/browserlayer.xml
src/collective/volto/cookieconsent/profiles/default/controlpanel.xml
src/collective/volto/cookieconsent/profiles/default/metadata.xml
src/collective/volto/cookieconsent/profiles/default/registry.xml
src/collective/volto/cookieconsent/profiles/uninstall/browserlayer.xml
src/collective/volto/cookieconsent/profiles/uninstall/controlpanel.xml
src/collective/volto/cookieconsent/profiles/uninstall/registry.xml
src/collective/volto/cookieconsent/restapi/__init__.py
src/collective/volto/cookieconsent/restapi/configure.zcml
src/collective/volto/cookieconsent/restapi/controlpanel.py
