Metadata-Version: 2.1
Name: collective.volto.cookieconsent
Version: 1.1.1
Summary: Add-on for Volto to manage cookieconsent banners
Home-page: https://github.com/collective/collective.volto.cookieconsent
Author: RedTurtle Technology
Author-email: sviluppoplone@redturtle.it
License: GPL version 2
Project-URL: PyPI, https://pypi.python.org/pypi/collective.volto.cookieconsent
Project-URL: Source, https://github.com/collective/collective.volto.cookieconsent
Project-URL: Tracker, https://github.com/collective/collective.volto.cookieconsent/issues
Keywords: Python Plone
Platform: UNKNOWN
Classifier: Environment :: Web Environment
Classifier: Framework :: Plone
Classifier: Framework :: Plone :: Addon
Classifier: Framework :: Plone :: 5.2
Classifier: Programming Language :: Python
Classifier: Programming Language :: Python :: 3.6
Classifier: Programming Language :: Python :: 3.7
Classifier: Operating System :: OS Independent
Classifier: License :: OSI Approved :: GNU General Public License v2 (GPLv2)
Requires-Python: >=3.6
Provides-Extra: test
